{
  "scanTime": "2026-4-3 21:00:23",
  "totalTokens": 3357,
  "filteredTokens": 21,
  "tokens": [
    {
      "address": "0xb8259393526035d4cd02c93fd0c2ef413b5c4444",
      "name": "CZ新书首批读者空投瓜分百万BNB",
      "symbol": "Freedom of Money",
      "holders": 468,
      "created_at": 1775207887000,
      "total_supply": 0,
      "price": 0.000037772949767111,
      "day1_vol": 12339.19,
      "progress": 0.9151830025
    },
    {
      "address": "0x69fd5a15fbc44433183296c14b54132741db4444",
      "name": "CZ新书首批读者空投瓜分百万BNB",
      "symbol": "我的币安人生",
      "holders": 338,
      "created_at": 1775127526000,
      "total_supply": 0,
      "price": 0.000003865117102883,
      "day1_vol": 13263.647747750121,
      "progress": 0.0067179049
    },
    {
      "address": "0x5b5b4bbd2fa6c271f177359665d534b0f88c4444",
      "name": "CZ新书首批读者空投瓜分30万枚BNB",
      "symbol": "幸运韧性与保护用户的回忆录",
      "holders": 313,
      "created_at": 1775034346000,
      "total_supply": 0,
      "price": 0.000003838579696819,
      "day1_vol": 0.98,
      "progress": 0.0021086181
    },
    {
      "address": "0xbc1ed24e9eda663d02202dfc0c441f7c156d4444",
      "name": "Michael4月24日全球上映",
      "symbol": "巨星之路",
      "holders": 293,
      "created_at": 1775179824000,
      "total_supply": 0,
      "price": 3.8536776489e-8,
      "day1_vol": 129568.93,
      "progress": 0.8243655665
    },
    {
      "address": "0x2c179abfbc60c638fc2302a21186845817494444",
      "name": "Aster Angels",
      "symbol": "ASTERANGEL",
      "holders": 221,
      "created_at": 1775140042000,
      "total_supply": 0,
      "price": 5.742434069e-9,
      "day1_vol": 46917.15,
      "progress": 0.000308409
    },
    {
      "address": "0x69126320f2605f50b35b4921330628712d494444",
      "name": "Grok",
      "symbol": "Grok",
      "holders": 213,
      "created_at": 1775219903000,
      "total_supply": 0,
      "price": 5.8181624269e-8,
      "day1_vol": 10972.69,
      "progress": 0.9208095245
    },
    {
      "address": "0xbafea2934f4e7998e07965ee264dd9ca34a84444",
      "name": "to the fucking moon",
      "symbol": "MOON",
      "holders": 208,
      "created_at": 1775080110000,
      "total_supply": 0,
      "price": 1.4288682282e-8,
      "day1_vol": 39087.2761278863,
      "progress": 0.4916111531
    },
    {
      "address": "0x1c370ff80ef38e583f3060aa99ebbb56ab104444",
      "name": "Astherus",
      "symbol": "ASTHERUS",
      "holders": 185,
      "created_at": 1775164873000,
      "total_supply": 0,
      "price": 5.740099959e-9,
      "day1_vol": 41373.63,
      "progress": 0.0000355544
    },
    {
      "address": "0xec0f93640ac957b6db9049ac1742ffe924904444",
      "name": "币安之王",
      "symbol": "币安之王",
      "holders": 173,
      "created_at": 1775136153000,
      "total_supply": 0,
      "price": 5.778652253e-9,
      "day1_vol": 39330.99,
      "progress": 0.0045210615
    },
    {
      "address": "0x17cc4caa532ad0cef9d36cb7a9cececfcb764444",
      "name": "币安之王",
      "symbol": "币安之王",
      "holders": 160,
      "created_at": 1775148639000,
      "total_supply": 0,
      "price": 5.803547173e-9,
      "day1_vol": 36492.08,
      "progress": 0.0073937721
    },
    {
      "address": "0xd2f552d4d94f94a5d9c9c7352663eace3933ffff",
      "name": "Dex Terminal",
      "symbol": "DEX",
      "holders": 159,
      "created_at": 1775044633000,
      "total_supply": 0,
      "price": 2.24335711e-8,
      "day1_vol": 5414.088155788962,
      "progress": 0.6634150009
    },
    {
      "address": "0x9f8e3f048f40b0dd3d976375ba230c4a322f4444",
      "name": "Astherus",
      "symbol": "ASTHERUS",
      "holders": 157,
      "created_at": 1775163054000,
      "total_supply": 0,
      "price": 5.79001089e-9,
      "day1_vol": 35798.37,
      "progress": 0.0058340719
    },
    {
      "address": "0x3b486c191c74c9945fa944a3ddde24acdd63ffff",
      "name": "BSC第一个具有代币经济的NFA项目",
      "symbol": "Claworld",
      "holders": 155,
      "created_at": 1775054049000,
      "total_supply": 0,
      "price": 2.5371007931e-8,
      "day1_vol": 18942.63256849625,
      "progress": 0.7039338803
    },
    {
      "address": "0x20ba337adfef39cca70b1ab28cd7033f983d4444",
      "name": "#1",
      "symbol": "#1",
      "holders": 134,
      "created_at": 1775197302000,
      "total_supply": 0,
      "price": 1.9696203783e-8,
      "day1_vol": 196835.36,
      "progress": 0.6177625575
    },
    {
      "address": "0x2d1c122a5df2cb72b38c0d67fb38dba18b554444",
      "name": "Shit期刊官方名字",
      "symbol": "S.H.*.T",
      "holders": 120,
      "created_at": 1775102880000,
      "total_supply": 0,
      "price": 2.4844732911e-8,
      "day1_vol": 52096.25072678221,
      "progress": 0.6972064501
    },
    {
      "address": "0xb57b0f6886f0b6669757e73e94b9fc4a6bfa4444",
      "name": "MIA",
      "symbol": "MIA",
      "holders": 115,
      "created_at": 1775220564000,
      "total_supply": 0,
      "price": 1.675607069e-8,
      "day1_vol": 113681.66,
      "progress": 0.5567502019
    },
    {
      "address": "0xea6e0b7629a1bb5cc31a153ef2203ab1b1894444",
      "name": "同事.skill",
      "symbol": "同事.skill",
      "holders": 114,
      "created_at": 1775143638000,
      "total_supply": 0,
      "price": 1.7396787702e-8,
      "day1_vol": 126743.62,
      "progress": 0.5713547343
    },
    {
      "address": "0xa80db58e6703d1c14aae0e3643b14efb68cf4444",
      "name": "币安之王",
      "symbol": "币安之王",
      "holders": 103,
      "created_at": 1775147560000,
      "total_supply": 0,
      "price": 5.742014313e-9,
      "day1_vol": 32933.25,
      "progress": 0.0002593522
    },
    {
      "address": "0xd76ad5f4223714f925c40f54aa934dca7c3b4444",
      "name": "BNB AI域名",
      "symbol": "agent.bnb",
      "holders": 97,
      "created_at": 1775138444000,
      "total_supply": 0,
      "price": 1.0179219446e-8,
      "day1_vol": 222321.85,
      "progress": 0.3343876012
    },
    {
      "address": "0x4ababa0213e6d12562a00eba5c20ccd238e84444",
      "name": "何一的Ai天线宝宝",
      "symbol": "Blob",
      "holders": 95,
      "created_at": 1775202328000,
      "total_supply": 0,
      "price": 8.015888767e-9,
      "day1_vol": 151427.48,
      "progress": 0.2064728979
    },
    {
      "address": "0x04b1dd885b27a78adb025b38248c7809874e4444",
      "name": "💁‍♀️",
      "symbol": "💁‍♀️",
      "holders": 94,
      "created_at": 1775119186000,
      "total_supply": 0,
      "price": 1.5963377238e-8,
      "day1_vol": 50703.88,
      "progress": 0.537478409
    }
  ]
}